lgedv/__init__.py
lgedv/server.py
codeguard_taikt-0.1.0.dist-info/METADATA
codeguard_taikt-0.1.0.dist-info/WHEEL
codeguard_taikt-0.1.0.dist-info/entry_points.txt
codeguard_taikt-0.1.0.dist-info/RECORD
