Metadata-Version: 2.4
Name: codeguard-taikt
Version: 0.1.0
Summary: A simple MCP server taikt
Author: Tran Anh Tai
License: MIT
Keywords: automation,fetch,llm,mcp,web
Classifier: Development Status :: 4 - Beta
Classifier: Intended Audience :: Developers
Classifier: License :: OSI Approved :: MIT License
Classifier: Programming Language :: Python :: 3
Classifier: Programming Language :: Python :: 3.10
Requires-Python: >=3.10
Requires-Dist: anyio>=4.5
Requires-Dist: click>=8.1.0
Requires-Dist: httpx>=0.27
Requires-Dist: mcp
